aiohttp_compress/__init__.py
aiohttp_compress/middleware.py
aiohttp_compress/version.py
aiohttp_compress-0.2.1.dist-info/LICENSE
aiohttp_compress-0.2.1.dist-info/LICENSE.md
aiohttp_compress-0.2.1.dist-info/METADATA
aiohttp_compress-0.2.1.dist-info/WHEEL
aiohttp_compress-0.2.1.dist-info/top_level.txt
aiohttp_compress-0.2.1.dist-info/RECORD
