Metadata-Version: 2.1
Name: aiohttp-compress
Version: 0.2.1
Summary: This module is the simplest way to enable compression support for aiohttp server applications globally.
Home-page: UNKNOWN
Author: Dmitry Orlov <me@mosquito.su>
Author-email: me@mosquito.su
License: Apache Software License
Project-URL: Source, https://github.com/mosquito/aiohttp-compress
Platform: all
Classifier: Development Status :: 4 - Beta
Classifier: License :: OSI Approved :: Apache Software License
Classifier: Topic :: Internet
Classifier: Topic :: Software Development
Classifier: Topic :: Software Development :: Libraries
Classifier: Intended Audience :: Developers
Classifier: Natural Language :: English
Classifier: Operating System :: MacOS
Classifier: Operating System :: POSIX
Classifier: Operating System :: Microsoft
Classifier: Programming Language :: Python
Classifier: Programming Language :: Python :: 3
Classifier: Programming Language :: Python :: 3.6
Classifier: Programming Language :: Python :: 3.7
Classifier: Programming Language :: Python :: 3.8
Classifier: Programming Language :: Python :: 3.9
Classifier: Programming Language :: Python :: Implementation :: PyPy
Classifier: Programming Language :: Python :: Implementation :: CPython
Requires-Python: >3.6.*, <4
Requires-Dist: aiohttp (<4)
Provides-Extra: develop
Requires-Dist: coverage (!=4.3) ; extra == 'develop'
Requires-Dist: coveralls ; extra == 'develop'
Requires-Dist: pylava ; extra == 'develop'
Requires-Dist: pytest ; extra == 'develop'
Requires-Dist: pytest-aiohttp ; extra == 'develop'
Requires-Dist: pytest-cov ; extra == 'develop'
Requires-Dist: tox (>=2.4) ; extra == 'develop'
